{
  "unversionedId": "Live Events/Set Up Pageviews",
  "id": "Live Events/Set Up Pageviews",
  "isDocsHomePage": false,
  "title": "Set Up Pageviews",
  "description": "This section serves as a comprehensive step-by-step guide for initiating your project. It provides detailed information on what actions to take, the methodology to follow, and the optimal timing for each step in the process.",
  "source": "@site/docs/Live Events/Set Up Pageviews.md",
  "sourceDirName": "Live Events",
  "slug": "/Live Events/Set Up Pageviews",
  "permalink": "/Wring_docs/docs/Live Events/Set Up Pageviews",
  "tags": [],
  "version": "current",
  "sidebarPosition": 2,
  "frontMatter": {
    "sidebar_position": 2
  },
  "sidebar": "tutorialSidebar",
  "previous": {
    "title": "Apps",
    "permalink": "/Wring_docs/docs/Live Events/Apps"
  },
  "next": {
    "title": "capture-api-calls",
    "permalink": "/Wring_docs/docs/Live Events/capture-api-calls"
  }
}